{"cameraMode":{"drawMode":0,"name":"Shaded","section":"Shading Mode"},"sceneLighting":true,"audioPlay":false,"sceneViewState":{"showFog":true,"showMaterialUpdate":false,"showSkybox":true,"showFlares":true,"showImageEffects":true,"showParticleSystems":true,"showVisualEffectGraphs":true,"m_FxEnabled":true},"in2DMode":false,"pivot":{"x":60.66266632080078,"y":5.487879753112793,"z":-114.13938903808594},"rotation":{"x":0.07420457899570465,"y":-0.6282537579536438,"z":0.05884169414639473,"w":0.7725878357887268},"size":24.72028160095215,"orthographic":false}