{"cameraMode":{"drawMode":0,"name":"Shaded","section":"Shading Mode"},"sceneLighting":true,"audioPlay":false,"sceneViewState":{"showFog":true,"showMaterialUpdate":false,"showSkybox":true,"showFlares":true,"showImageEffects":true,"showParticleSystems":true,"showVisualEffectGraphs":true,"m_FxEnabled":true},"in2DMode":false,"pivot":{"x":57.75333786010742,"y":-62.40694046020508,"z":-90.7014389038086},"rotation":{"x":0.36390313506126406,"y":-0.5648159384727478,"z":0.3038856089115143,"w":0.6758027076721191},"size":62.839935302734378,"orthographic":false}